README.rst
setup.py
E26/__init__.py
E26.egg-info/PKG-INFO
E26.egg-info/SOURCES.txt
E26.egg-info/dependency_links.txt
E26.egg-info/not-zip-safe
E26.egg-info/top_level.txt