Metadata-Version: 1.0
Name: E26
Version: 0.4
Summary: E26 is a new password/string encoder/decoder method.
Home-page: UNKNOWN
Author: KyrosDesign
Author-email: alexv6558@gmail.com
License: MIT
Platform: UNKNOWN
